MANIFEST.in
README.rst
setup.py
tox.ini
docs/index.rst
octogit/__init__.py
octogit/__main__.py
octogit/cli.py
octogit/config.py
octogit/core.py
octogit.egg-info/PKG-INFO
octogit.egg-info/SOURCES.txt
octogit.egg-info/dependency_links.txt
octogit.egg-info/entry_points.txt
octogit.egg-info/requires.txt
octogit.egg-info/top_level.txt
tests/cli.py
tests/cli.pyc
tests/config.py
tests/config.pyc
tests/core.py
tests/core.pyc