Metadata-Version: 1.1
Name: octogit
Version: 0.3.3
Summary: giving git tentacles to work better with github
Home-page: https://github.com/myusuf3/octogit
Author: Mahdi Yusuf
Author-email: yusuf.mahdi@gmail.com
License: MIT License
Platform: UNKNOWN
Classifier: Development Status :: 4 - Beta
Classifier: Intended Audience :: Developers
Classifier: Natural Language :: English
Classifier: License :: OSI Approved :: MIT License
Classifier: Programming Language :: Python
Classifier: Programming Language :: Python :: 2.6
Classifier: Programming Language :: Python :: 2.7
